{
  "projectA1": "기업 홍보 AI 영상 - 대외 신뢰 확보를 위한 기업 비전·연혁 중심",
  "projectA2": "기업 홍보 AI 영상 - 채용 브랜딩 강화를 위한 조직문화·근무환경 중심",
  "projectB1": "제품 광고 AI 영상 - 신규 고객 유입을 위한 핵심 USP 강조형 퍼포먼스 광고",
  "projectB2": "제품 광고 AI 영상 - 기존 관심 고객 전환을 위한 사용 장면·후기 기반 설득형 광고",
  "projectC1": "브랜드 소개 AI 영상 - 브랜드 철학과 세계관을 전달하는 아이덴티티 필름",
  "projectC2": "브랜드 소개 AI 영상 - 브랜드 톤앤매너를 명확히 각인시키는 캠페인형 소개 영상",
  "projectD1": "시네마틱 AI 필름 - 세계관과 감정선을 영화적 연출로 전달하는 메인 필름형 콘텐츠",
  "projectD2": "브랜드 서비스 홍보 AI 영상 - 서비스의 포인트를 명확하게 전달해 전환율을 높이는 프로모션 콘텐츠"
}
